novelsave_sources/__init__.py
novelsave_sources/exceptions.py
novelsave_sources/models/__init__.py
novelsave_sources/models/chapter.py
novelsave_sources/models/metadata.py
novelsave_sources/models/novel.py
novelsave_sources/models/volume.py
novelsave_sources/sources/__init__.py
novelsave_sources/sources/crawler.py
novelsave_sources/sources/metadata/__init__.py
novelsave_sources/sources/metadata/metasource.py
novelsave_sources/sources/metadata/novelupdates.py
novelsave_sources/sources/metadata/wlnupdates.py
novelsave_sources/sources/novel/1stkissnovel.py
novelsave_sources/sources/novel/__init__.py
novelsave_sources/sources/novel/betwixtedbutterfly.py
novelsave_sources/sources/novel/boxnovel_com.py
novelsave_sources/sources/novel/cclawtranslations.py
novelsave_sources/sources/novel/chickengege.py
novelsave_sources/sources/novel/chrysagarden.py
novelsave_sources/sources/novel/creativenovels.py
novelsave_sources/sources/novel/domentranslations.py
novelsave_sources/sources/novel/dragontea.py
novelsave_sources/sources/novel/dummynovels.py
novelsave_sources/sources/novel/foxaholic.py
novelsave_sources/sources/novel/lightnovelworld.py
novelsave_sources/sources/novel/mtlnovel.py
novelsave_sources/sources/novel/novelfull.py
novelsave_sources/sources/novel/novelfun.py
novelsave_sources/sources/novel/novelgate.py
novelsave_sources/sources/novel/novelhall.py
novelsave_sources/sources/novel/novelonlinefull.py
novelsave_sources/sources/novel/novelpassion.py
novelsave_sources/sources/novel/novelpub.py
novelsave_sources/sources/novel/novelsite.py
novelsave_sources/sources/novel/novelsonline.py
novelsave_sources/sources/novel/novelsrock.py
novelsave_sources/sources/novel/peachpitting.py
novelsave_sources/sources/novel/qidian.py
novelsave_sources/sources/novel/rainofsnow.py
novelsave_sources/sources/novel/readlightnovel_me.py
novelsave_sources/sources/novel/readlightnovels_net.py
novelsave_sources/sources/novel/readnovelfull.py
novelsave_sources/sources/novel/royalroad.py
novelsave_sources-0.3.3.dist-info/LICENSE
novelsave_sources-0.3.3.dist-info/WHEEL
novelsave_sources-0.3.3.dist-info/METADATA
novelsave_sources-0.3.3.dist-info/RECORD
