Metadata-Version: 2.1
Name: novelsave-sources
Version: 0.3.3
Summary: A collection of novel sources offering varying amounts of scraping capability.
Home-page: https://github.com/mensch272/novelsave_sources
License: Apache-2.0
Keywords: webnovel,novel,lightnovel,scraper,crawler
Author: Mensch272
Author-email: 47662901+mensch272@users.noreply.github.com
Maintainer: Mensch272
Maintainer-email: 47662901+mensch272@users.noreply.github.com
Requires-Python: >=3.8,<4.0
Classifier: Development Status :: 5 - Production/Stable
Classifier: Intended Audience :: Developers
Classifier: License :: OSI Approved :: Apache Software License
Classifier: Natural Language :: English
Classifier: Programming Language :: Python :: 3
Classifier: Programming Language :: Python :: 3 :: Only
Classifier: Programming Language :: Python :: 3.10
Classifier: Programming Language :: Python :: 3.8
Classifier: Programming Language :: Python :: 3.9
Classifier: Topic :: Games/Entertainment
Provides-Extra: docs
Requires-Dist: beautifulsoup4 (>=4.10.0,<5.0.0)
Requires-Dist: cloudscraper (>=1.2.60,<2.0.0)
Requires-Dist: dateparser (>=1.1.0,<2.0.0)
Requires-Dist: deprecation (>=2.1.0,<3.0.0)
Requires-Dist: lxml (>=4.8.0,<5.0.0)
Requires-Dist: requests (>=2.27.1,<3.0.0)
Requires-Dist: sphinx (>=4.4.0,<5.0.0); extra == "docs"
Requires-Dist: sphinx_rtd_theme (>=1.0.0,<2.0.0); extra == "docs"
Project-URL: Documentation, https://novelsave-sources.readthedocs.io/en/latest/
Project-URL: Issue Tracker, https://github.com/mensch272/novelsave_sources/issues
Project-URL: Repository, https://github.com/mensch272/novelsave_sources
Project-URL: Source Code, https://github.com/mensch272/novelsave_sources
